pymotego/__init__.py
pymotego/_constants.py
pymotego/broadcast.py
pymotego/py.typed
pymotego/send_email.py
pymotego-0.1.3.dist-info/WHEEL
pymotego-0.1.3.dist-info/METADATA
pymotego-0.1.3.dist-info/RECORD
