Metadata-Version: 2.3
Name: pymotego
Version: 0.1.3
Summary: `python` binding for `cogmoteGO`
Author: HuYang
Author-email: HuYang <hy.ccccr@gmail.com>
Requires-Dist: httpx[http2]>=0.28.1
Requires-Dist: pyzmq>=27.0.1
Requires-Python: >=3.13
